Koptool-2.9.dist-info/DESCRIPTION.rst
Koptool-2.9.dist-info/METADATA
Koptool-2.9.dist-info/RECORD
Koptool-2.9.dist-info/WHEEL
Koptool-2.9.dist-info/entry_points.txt
Koptool-2.9.dist-info/metadata.json
Koptool-2.9.dist-info/top_level.txt
Koptool-2.9.dist-info/zip-safe
koptool/__init__.py
koptool/get_api.py
koptool/kop.py
koptool/list_api.py
koptool/list_service.py
koptool/modify_api.py
koptool/offline_api.py
koptool/online_api.py
