Metadata-Version: 2.0
Name: Koptool
Version: 2.9
Summary: a tiny and smart cli player of douyutv,ximalayad,anmu based on Python
Home-page: UNKNOWN
Author: cjxcloud
Author-email: cjxcloud@163.com
License: MIT
Keywords: python ksyun tools terminal
Platform: UNKNOWN
Requires-Dist: requests
